{
  "version": "7",
  "dialect": "postgresql",
  "entries": [
    {
      "idx": 0,
      "version": "7",
      "when": 1772835394001,
      "tag": "0000_fine_spacker_dave",
      "breakpoints": true
    },
    {
      "idx": 1,
      "version": "7",
      "when": 1772836408028,
      "tag": "0001_unique_butterfly",
      "breakpoints": true
    },
    {
      "idx": 2,
      "version": "7",
      "when": 1772904483690,
      "tag": "0002_spooky_scalphunter",
      "breakpoints": true
    },
    {
      "idx": 3,
      "version": "7",
      "when": 1772905839587,
      "tag": "0003_loud_morlun",
      "breakpoints": true
    },
    {
      "idx": 4,
      "version": "7",
      "when": 1772982586729,
      "tag": "0004_quick_ego",
      "breakpoints": true
    },
    {
      "idx": 5,
      "version": "7",
      "when": 1773088772959,
      "tag": "0005_lame_madame_web",
      "breakpoints": true
    },
    {
      "idx": 6,
      "version": "7",
      "when": 1773089701456,
      "tag": "0006_elite_medusa",
      "breakpoints": true
    }
  ]
}